{
	"name": "siva",
	"properties": {
		"activities": [
			{
				"name": "Wait1",
				"description": "wait for 30 second ",
				"type": "Wait",
				"dependsOn": [],
				"userProperties": [],
				"typeProperties": {
					"waitTimeInSeconds": 30
				}
			},
			{
				"name": "Execute Pipeline1",
				"type": "ExecutePipeline",
				"dependsOn": [
					{
						"activity": "Wait1",
						"dependencyConditions": [
							"Succeeded"
						]
					}
				],
				"policy": {
					"secureInput": false
				},
				"userProperties": [],
				"typeProperties": {
					"pipeline": {
						"referenceName": "siva 2",
						"type": "PipelineReference"
					},
					"waitOnCompletion": true
				}
			}
		],
		"annotations": [],
		"lastPublishTime": "2025-06-24T10:32:02Z"
	},
	"type": "Microsoft.DataFactory/factories/pipelines"
}