{
	"name": "Text11",
	"properties": {
		"linkedServiceName": {
			"referenceName": "AzureDataLakeStorage1",
			"type": "LinkedServiceReference"
		},
		"annotations": [],
		"type": "DelimitedText",
		"typeProperties": {
			"location": {
				"type": "AzureBlobFSLocation",
				"fileName": "Salary_Data.csv",
				"folderPath": "day 1",
				"fileSystem": "batch135"
			},
			"columnDelimiter": ",",
			"escapeChar": "\\",
			"firstRowAsHeader": true,
			"quoteChar": "\""
		},
		"schema": [
			{
				"name": "YearsExperience",
				"type": "String"
			},
			{
				"name": "Salary",
				"type": "String"
			}
		]
	}
}